mkdocs_localsearch_plugin/__init__.py
mkdocs_localsearch_plugin/plugin.py
mkdocs_localsearch-0.9.2.dist-info/LICENSE
mkdocs_localsearch-0.9.2.dist-info/METADATA
mkdocs_localsearch-0.9.2.dist-info/WHEEL
mkdocs_localsearch-0.9.2.dist-info/entry_points.txt
mkdocs_localsearch-0.9.2.dist-info/top_level.txt
mkdocs_localsearch-0.9.2.dist-info/RECORD
