Metadata-Version: 2.1
Name: mkdocs-localsearch
Version: 0.9.2
Summary: A MkDocs plugin to replace the native "search" plugin with a search plugin that also works locally (file:// protocol). Only works with the Material theme.
Home-page: https://github.com/wilhelmer/mkdocs-localsearch
Author: Lars Wilhelmer
Author-email: lars@wilhelmer.de
License: MIT
Keywords: mkdocs local search
Classifier: Development Status :: 4 - Beta
Classifier: Intended Audience :: Developers
Classifier: Intended Audience :: Information Technology
Classifier: License :: OSI Approved :: MIT License
Classifier: Programming Language :: Python
Classifier: Programming Language :: Python :: 3 :: Only
Classifier: Programming Language :: Python :: 3.4
Classifier: Programming Language :: Python :: 3.5
Classifier: Programming Language :: Python :: 3.6
Classifier: Programming Language :: Python :: 3.7
Requires-Python: >=3.5
License-File: LICENSE
Requires-Dist: mkdocs (>=1.1)
